<?xml version="1.0" encoding="utf-8" ?>
<Patch>
	<Operation Class="PatchOperationFindMod">
		<mods>
			<li>Call of Duty: Pack A Punch</li>
        	<li>Call of Duty: Zombies Pack</li>
		</mods>
		<match Class="PatchOperationSequence">
			<operations>
				<li Class="PatchOperationAdd">
					<xpath>Defs</xpath>
					<value>
  <RecipeDef ParentName="AmmoRecipePunched">
		<defName>MakeAmmo_762x51mmNATO_FMJ_Punched</defName>
		<label>make 7.62x51mm NATO (FMJ) cartridge (Punched) x500</label>
		<description>Craft 500 7.62x51mm NATO (FMJ) cartridges (Punched).</description>
		<jobString>Making 7.62x51mm NATO (FMJ) cartridges.</jobString>
		<ingredients>
			<li>
				<filter>
					<thingDefs>
						<li>Ammo_762x51mmNATO_FMJ</li>
					</thingDefs>
				</filter>
				<count>2000</count>
			</li>
		</ingredients>
		<fixedIngredientFilter>
			<thingDefs>
				<li>Ammo_762x51mmNATO_FMJ</li>
			</thingDefs>
		</fixedIngredientFilter>
		<products>
			<Ammo_762x51mmNATO_FMJ_Punched>500</Ammo_762x51mmNATO_FMJ_Punched>
		</products>
	<workAmount>2600</workAmount>		
	</RecipeDef>

	<RecipeDef ParentName="AmmoRecipePunched">
		<defName>MakeAmmo_762x51mmNATO_AP_Punched</defName>
		<label>make 7.62x51mm NATO (AP) cartridge (Punched) x500</label>
		<description>Craft 500 7.62x51mm NATO (AP) cartridges (Punched).</description>
		<jobString>Making 7.62x51mm NATO (AP) cartridges.</jobString>
		<ingredients>
			<li>
				<filter>
					<thingDefs>
						<li>Ammo_762x51mmNATO_AP</li>
					</thingDefs>
				</filter>
				<count>2000</count>
			</li>
		</ingredients>
		<fixedIngredientFilter>
			<thingDefs>
				<li>Ammo_762x51mmNATO_AP</li>
			</thingDefs>
		</fixedIngredientFilter>
		<products>
			<Ammo_762x51mmNATO_AP_Punched>500</Ammo_762x51mmNATO_AP_Punched>
		</products>
	<workAmount>2600</workAmount>		
	</RecipeDef>

	<RecipeDef ParentName="AmmoRecipePunched">
		<defName>MakeAmmo_762x51mmNATO_HP_Punched</defName>
		<label>make 7.62x51mm NATO (HP) cartridge (Punched) x500</label>
		<description>Craft 500 7.62x51mm NATO (HP) cartridges (Punched).</description>
		<jobString>Making 7.62x51mm NATO (HP) cartridges.</jobString>
		<ingredients>
			<li>
				<filter>
					<thingDefs>
						<li>Ammo_762x51mmNATO_HP</li>
					</thingDefs>
				</filter>
				<count>2000</count>
			</li>
		</ingredients>
		<fixedIngredientFilter>
			<thingDefs>
				<li>Ammo_762x51mmNATO_HP</li>
			</thingDefs>
		</fixedIngredientFilter>
		<products>
			<Ammo_762x51mmNATO_HP_Punched>500</Ammo_762x51mmNATO_HP_Punched>
		</products>
	<workAmount>2600</workAmount>		
	</RecipeDef>

  <RecipeDef ParentName="AmmoRecipePunched">
    <defName>MakeAmmo_762x51mmNATO_Incendiary_Punched</defName>
    <label>make 7.62x51mm NATO (AP-I) cartridge (Punched) x500</label>
    <description>Craft 500 7.62x51mm NATO (AP-I) cartridges (Punched).</description>
    <jobString>Making 7.62x51mm NATO (AP-I) cartridges.</jobString>
    <ingredients>
      <li>
        <filter>
          <thingDefs>
            <li>Ammo_762x51mmNATO_Incendiary</li>
          </thingDefs>
        </filter>
        <count>2000</count>
      </li>
    </ingredients>
    <fixedIngredientFilter>
      <thingDefs>
        <li>Ammo_762x51mmNATO_Incendiary</li>
      </thingDefs>
    </fixedIngredientFilter>
    <products>
      <Ammo_762x51mmNATO_Incendiary_Punched>500</Ammo_762x51mmNATO_Incendiary_Punched>
    </products>
    <workAmount>3800</workAmount>
  </RecipeDef>
  
  <RecipeDef ParentName="AmmoRecipePunched">
    <defName>MakeAmmo_762x51mmNATO_HE_Punched</defName>
    <label>make 7.62x51mm NATO (HE) cartridge (Punched) x500</label>
    <description>Craft 500 7.62x51mm NATO (HE) cartridges (Punched).</description>
    <jobString>Making 7.62x51mm NATO (HE) cartridges.</jobString>
    <ingredients>
      <li>
        <filter>
          <thingDefs>
            <li>Ammo_762x51mmNATO_HE</li>
          </thingDefs>
        </filter>
        <count>2000</count>
      </li>
    </ingredients>
    <fixedIngredientFilter>
      <thingDefs>
        <li>Ammo_762x51mmNATO_HE</li>
      </thingDefs>
    </fixedIngredientFilter>
    <products>
      <Ammo_762x51mmNATO_HE_Punched>500</Ammo_762x51mmNATO_HE_Punched>
    </products>
    <workAmount>4600</workAmount>
  </RecipeDef>
  
  <RecipeDef ParentName="AmmoRecipePunched">
    <defName>MakeAmmo_762x51mmNATO_Sabot_Punched</defName>
    <label>make 7.62x51mm NATO (Sabot) cartridge (Punched) x500</label>
    <description>Craft 500 7.62x51mm NATO (Sabot) cartridges (Punched).</description>
    <jobString>Making 7.62x51mm NATO (Sabot) cartridges.</jobString>
    <ingredients>
      <li>
        <filter>
          <thingDefs>
            <li>Ammo_762x51mmNATO_Sabot</li>
          </thingDefs>
        </filter>
        <count>2000</count>
      </li>		  
    </ingredients>
    <fixedIngredientFilter>
      <thingDefs>
        <li>Ammo_762x51mmNATO_Sabot</li>		
      </thingDefs>
    </fixedIngredientFilter>
    <products>
      <Ammo_762x51mmNATO_Sabot_Punched>500</Ammo_762x51mmNATO_Sabot_Punched>
    </products>
    <workAmount>3400</workAmount>
  </RecipeDef>
					</value>
				</li>
			</operations>
		</match>
	</Operation>
</Patch>