<?xml version="1.0" encoding="utf-8" ?>
<Patch>

	<!-- ========== Mark II Crusader  ========== -->

	<Operation Class="PatchOperationAdd">
		<xpath>Defs/ThingDef[defName="GW_SM_CrusaderArmor"]/statBases</xpath>
		<value>
			<Bulk>225</Bulk>
			<WornBulk>20</WornBulk>
		</value>
	</Operation>

	<Operation Class="PatchOperationReplace">
		<xpath>Defs/ThingDef[defName="GW_SM_CrusaderArmor"]/statBases/ArmorRating_Sharp</xpath>
		<value>
			<ArmorRating_Sharp>36</ArmorRating_Sharp>
		</value>
	</Operation>

	<Operation Class="PatchOperationReplace">
		<xpath>Defs/ThingDef[defName="GW_SM_CrusaderArmor"]/statBases/ArmorRating_Blunt</xpath>
		<value>
			<ArmorRating_Blunt>360</ArmorRating_Blunt>
		</value>
	</Operation>

	<!-- ========== Mark III Iron  ========== -->

	<Operation Class="PatchOperationAdd">
		<xpath>Defs/ThingDef[defName="GW_SM_IronArmor"]/statBases</xpath>
		<value>
			<Bulk>200</Bulk>
			<WornBulk>20</WornBulk>
		</value>
	</Operation>

	<Operation Class="PatchOperationReplace">
		<xpath>Defs/ThingDef[defName="GW_SM_IronArmor"]/statBases/ArmorRating_Sharp</xpath>
		<value>
			<ArmorRating_Sharp>40</ArmorRating_Sharp>
		</value>
	</Operation>

	<Operation Class="PatchOperationReplace">
		<xpath>Defs/ThingDef[defName="GW_SM_IronArmor"]/statBases/ArmorRating_Blunt</xpath>
		<value>
			<ArmorRating_Blunt>370</ArmorRating_Blunt>
		</value>
	</Operation>

	<!-- ========== Mark III Heresy ========== -->

	<Operation Class="PatchOperationAdd">
		<xpath>Defs/ThingDef[defName="GW_SM_HeresyArmor"]/statBases</xpath>
		<value>
			<Bulk>300</Bulk>
			<WornBulk>40</WornBulk>
		</value>
	</Operation>

	<Operation Class="PatchOperationReplace">
		<xpath>Defs/ThingDef[defName="GW_SM_HeresyArmor"]/statBases/ArmorRating_Sharp</xpath>
		<value>
			<ArmorRating_Sharp>46</ArmorRating_Sharp>
		</value>
	</Operation>

	<Operation Class="PatchOperationReplace">
		<xpath>Defs/ThingDef[defName="GW_SM_HeresyArmor"]/statBases/ArmorRating_Blunt</xpath>
		<value>
			<ArmorRating_Blunt>380</ArmorRating_Blunt>
		</value>
	</Operation>

</Patch>